dao/__init__.py
dao/main.py
dao0-1.0.7.dist-info/LICENSE
dao0-1.0.7.dist-info/METADATA
dao0-1.0.7.dist-info/WHEEL
dao0-1.0.7.dist-info/top_level.txt
dao0-1.0.7.dist-info/RECORD
