Metadata-Version: 2.1
Name: dao0
Version: 1.0.7
Summary: dao sheng wan wu
Home-page: https://github.com/DJMIN/dao
Author: readerror
Author-email: readerror@sina.com
Maintainer: readerror
Maintainer-email: readerror@sina.com
License: GPL License
Platform: all
Requires-Python: >=3.5
License-File: LICENSE
Requires-Dist: requests
Requires-Dist: wrapt
Requires-Dist: wheel
Requires-Dist: twine
Requires-Dist: tqdm
